{"disable-sprite-wobble/@name":"Correggi il glitch dell'area degli sprite","disable-sprite-wobble/@description":"Corregge un bug dell'editor di Scratch permettendo di trascinare script, costumi e suoni sugli sprite ma evitando che questi cambino posizione nell'area degli sprite.","disable-sprite-wobble/@update":"Questo addon è stato modificato, e ora corregge il bug dell'area degli sprite senza dover anche disabilitare l'animazione del tremolio degli sprite. Se vuoi disabilitare comunque il tremolio, c'è un'impostazione apposita sotto. ","disable-sprite-wobble/@settings-name-mode":"Modalità","disable-sprite-wobble/@settings-select-mode-none":"Correggi il bug e lascia attivo il tremolio","disable-sprite-wobble/@settings-select-mode-no-wobble":"Correggi il bug e disabilita il tremolio"}