{"forum-search/loading":"Caricamento...","forum-search/error":"C'è stato un'errore durante il caricamento da ScratchDB!","forum-search/none":"Nessun risultato","forum-search/posts-here":"Post di questo Utente in questo Topic ","forum-search/posts-sitewide":"Post di questo Utente in Tutto il Sito","forum-search/last-edited-by":"Ultima modifica di {username} ({datetime})","forum-search/placeholder":"Ricerca nei post","forum-search/relevance":"rilevanza","forum-search/newest":"più recenti","forum-search/oldest":"più vecchi","forum-search/filter-placeholder":"Filtro (ad es. username = \"\")","forum-search/@name":"Cerca nei forum","forum-search/@description":"Aggiunge una barra di ricerca per post dei forum. Utilizza le informazioni di ScratchDB."}