{"msg-count-badge/@name":"Numero nuovi messaggi nell'icona dell'estensione","msg-count-badge/@description":"Mostra il numero dei nuovi messaggi nell'icona di ScratchAddons.","msg-count-badge/@info-dndtohide":"Puoi usare Non Disturbare (click destro sull'icona dell'estensione → Non disturbare) per nascondere temporaneamente il contatore dei messaggi.","msg-count-badge/@preset-name-oldLightGreen":"Verde chiaro precedente","msg-count-badge/@preset-description-oldLightGreen":"Il colore del badge dell'Estensione Scratch Messaging originale.","msg-count-badge/@preset-name-blue":"Azzurro","msg-count-badge/@preset-name-black":"Nero","msg-count-badge/@preset-name-orange":"Arancione","msg-count-badge/@preset-description-orange":"Lo stesso colore del logo di ScratchAddons.","msg-count-badge/@settings-name-color":"Colore badge","msg-count-badge/@settings-name-showOffline":"Indica quando non si è collegati"}