{
  "name": "2D color picker",
  "description": "Replaces saturation and brightness sliders in the costume editor with a 2D color picker. Hold Shift while dragging the cursor to change the values on a single axis.",
  "tags": ["editor", "costumeEditor"],
  "credits": [
    {
      "name": "Ucrash",
      "link": "https://github.com/gducrash"
    }
  ],
  "userscripts": [
    {
      "url": "userscript.js",
      "matches": ["projects"]
    }
  ],
  "userstyles": [
    {
      "url": "style.css",
      "matches": ["projects"]
    }
  ],
  "libraries": ["tinycolor2"],
  "versionAdded": "1.12.0",
  "enabledByDefault": false
}
