{"editor-dark-mode/@name":"Tema escuro no editor e cores customizadas","editor-dark-mode/@description":"Mude as cores usadas no editor de projeto. Vários temas escuros por autores diferentes estão disponíveis. Se você não quer um tema escuro mas quer mudar as cores do editor, você pode escolher a predefinição \"cores padrão do Scratch\" e ajustá-lo.","editor-dark-mode/@update":"Os presets desse addon foram atualizados para utilizar a nova coloração dos detalhes dos blocos do Scrach. Presets que utilizam a cor azul continuam disponíveis.","editor-dark-mode/@preset-name-3darker":"3.Mais preto","editor-dark-mode/@preset-description-3darker":"Um tema escuro baseado em um userscript por infinitytec","editor-dark-mode/@preset-name-3darker-blue":"3.Mais escuro (azul)","editor-dark-mode/@preset-description-3darker-blue":"3.Mais escuro com cor de destaque azul ","editor-dark-mode/@preset-name-3dark":"3.Preto","editor-dark-mode/@preset-description-3dark":"Um tema azul escuro baseado em um userscript por infinitytec","editor-dark-mode/@preset-name-darkEditor":"Escuro","editor-dark-mode/@preset-description-darkEditor":"Um tema escuro baseado em um userstyle por _nix","editor-dark-mode/@preset-name-experimentalDark":"\"Experimental\"","editor-dark-mode/@preset-description-experimentalDark":"Um tema escuro por Maximouse baseado em um userstyle. Apesar do nome, não é experimental","editor-dark-mode/@preset-name-tw-dark":"TurboWarp Escuro","editor-dark-mode/@preset-description-tw-dark":"Um tema escuro baseado no modo escuro do TurboWarp.","editor-dark-mode/@preset-description-scratch2":"Um tema baseado nas cores do Scratch 2.0.","editor-dark-mode/@preset-description-scratch1":"Um tema baseado nas cores do Scratch 1.x.","editor-dark-mode/@preset-name-scratch":"Cores padrão do Scratch","editor-dark-mode/@preset-description-scratch":"As cores normais do Scratch","editor-dark-mode/@preset-name-scratch-blue":"Cores padrões do Scratch (azul)","editor-dark-mode/@preset-description-scratch-blue":"As cores originalmente usadas pelo Scratch 3.0","editor-dark-mode/@credits-addon":"addon, tema \"Experimental\"","editor-dark-mode/@credits-darker":"tema Azulado, Preto","editor-dark-mode/@credits-dark":"tema Escuro","editor-dark-mode/@credits-twdark":"tema do TurboWarp","editor-dark-mode/@settings-name-page":"Fundo da página","editor-dark-mode/@settings-name-primary":"Cor de destaque","editor-dark-mode/@settings-name-highlightText":"Cor de destaque para texto e ícones","editor-dark-mode/@settings-name-menuBar":"Menu superior","editor-dark-mode/@settings-name-activeTab":"Aba ativa","editor-dark-mode/@settings-name-tab":"Aba inativa","editor-dark-mode/@settings-name-selector":"Painel de atores","editor-dark-mode/@settings-name-selector2":"Fundo da lista de sons/fantasias","editor-dark-mode/@settings-name-selectorSelection":"Fundo de ator/recurso selecionado","editor-dark-mode/@settings-name-accent":"Detalhes","editor-dark-mode/@settings-name-input":"Entrada de texto","editor-dark-mode/@settings-name-workspace":"Fundo da área de código","editor-dark-mode/@settings-name-categoryMenu":"Menu das categorias de bloco","editor-dark-mode/@settings-name-palette":"Paleta de blocos","editor-dark-mode/@settings-name-fullscreen":"Fundo em tela cheia","editor-dark-mode/@settings-name-stageHeader":"Fundo do cabeçalho em tela cheia","editor-dark-mode/@settings-name-border":"Borda","editor-dark-mode/@settings-name-dots":"Mostrar pontinhos na área de trabalho","editor-dark-mode/@settings-name-affectStage":"Mude a cor de variáveis, listas, balões de fala e entradas de texto no palco."}