{"scratchstats/title":"統計數據","scratchstats/view-more":"在 ScratchStats.com 上檢視","scratchstats/followers":"關注者","scratchstats/most-followed-global":"最多人關注","scratchstats/most-followed-location":"本地最多人關注","scratchstats/most-loves":"最多人喜愛","scratchstats/most-favorites":"最多人收藏","scratchstats/most-views":"最多人觀看","scratchstats/err":"無法載入統計數據。","scratchstats/err-chart":"無法載入統計圖表。","scratchstats/followers-title":"關注者變化趨勢","scratchstats/@name":"個人統計數據","scratchstats/@description":"在個人資料頁上顯示 ScratchDB 的統計數據。"}