{"debugger/console":"기록","debugger/debug":"디버그","debugger/export":"내보내기","debugger/clear":"지우기","debugger/close":"닫기","debugger/step":"절차","debugger/thread":"작업 {id}","debugger/enter-format":"내보낼 방법을 입력하세요:","debugger/unpause":"재개하기","debugger/unknown-sprite":"(알 수 없는 스프라이트)","debugger/clone-of":"{sprite}의 복제본","debugger/icon-warn":"경고","debugger/icon-error":"오류","debugger/empty-string":"(빈 문자열)","debugger/export-desc":"내보낼 방법을 개인 설정하려면 Shift키를 누른 상태로 클릭하세요.","debugger/block-breakpoint":"중단점","debugger/block-log":"기록 %s","debugger/block-warn":"경고 %s","debugger/block-error":"오류 %s","debugger/cannot-pause-player":"중단점 블록은 에디터에 있을 때에만 사용 가능합니다.","debugger/step-desc":"한 블록을 실행합니다.","debugger/tab-logs":"기록","debugger/tab-threads":"실행 중인 작업","debugger/tab-performance":"성능","debugger/no-logs":"표시할 기록이 없습니다.","debugger/no-threads-running":"실행 중인 작업 없음.","debugger/performance-clonecount-title":"복제본","debugger/performance-clonecount-graph-tooltip":"복제본: {clones}","debugger/log-msg-flag-clicked":"녹색 깃발이 클릭되었습니다.","debugger/log-msg-clone-cap":"'{sprite}'의 복제본을 생성하는 데 실패했습니다. 300개가 넘는 복제본을 만들 수 없습니다.","debugger/log-msg-clone-created":"'{sprite}'의 복제본이 만들어졌습니다.","debugger/log-msg-broadcasted":"신호 '{broadcast}'가 발송되었습니다.","debugger/log-msg-list-append-too-long":"리스트 '{list}'에 값을 추가하는 데 실패했습니다. 20만 개 이상의 항목을 추가할 수 없습니다.","debugger/log-msg-list-insert-too-long":"리스트 '{list}'의 20만 번째 항목이 삽입을 위한 공간을 만들기 위해 제거었습니다. 리스트에 20만 개 이상의 항목을 추가할 수 없습니다.","debugger/log-cloud-data-nan":"클라우드 변수 '{var}'의 값을 설정하는 데 실패했습니다. 클라우드 변수는 숫자만 담을 수 있습니다.","debugger/log-cloud-data-too-long":"클라우드 변수 '{var}'의 값을 설정하는 데 실패했습니다. 클라우드 변수는 최대 256 글자만 담을 수 있습니다.","debugger/@name":"디버거","debugger/@settings-name-log_clear_greenflag":"초록 깃발을 누르면 초기화하기","debugger/@settings-name-log_greenflag":"녹색 깃발 클릭 기록하기","debugger/@settings-name-log_clone_create":"복제본 생성 기록하기","debugger/@settings-name-log_broadcasts":"신호 기록하기","debugger/@settings-name-log_max_list_length":"리스트 항목 제한에 도달했을 때 기록하기","debugger/@settings-name-log_invalid_cloud_data":"클라우드 변수에 잘못된 값을 설정하려 할 때 기록하기"}