{"confirm-actions/@name":"Onaylamalar","confirm-actions/@description":"Scratch hesabınızdan proje paylaşma gibi eylemlerde emin olup olmadığınızı sorar.","confirm-actions/@settings-name-projectsharing":"Proje paylaşımını onayla","confirm-actions/@settings-name-projectunsharing":"Projenin paylaşımdan kaldırılmasını onaylayın","confirm-actions/@settings-name-followinguser":"Kullanıcıları takip etmeyi/takibi bırakmayı onayla","confirm-actions/@settings-name-joiningstudio":"Stüdyolara katılmayı onayla","confirm-actions/@settings-name-closingtopic":"Forum konularını kapatmayı onayla"}