{"studio-followers/modal-title":"Takipçileri stüdyoya davet edin","studio-followers/button":"Takipçilere Gözat","studio-followers/fetch-error":"Hmm, bunu yapmaya izniniz yok gibi görünüyor. Giriş yaptığınızdan emin olun.","studio-followers/followers":"Takipçiler","studio-followers/following":"Takip Edilen","studio-followers/@name":"Stüdyolarda takipçilere gözat düğmesi","studio-followers/@description":"Yönettiğiniz stüdyolarda \"yöneticiler\" sekmesinin üst kısmına takipçilerinizi ve takip ettiğiniz kullanıcıları listeleyen bir düğme ekler ve görülen bir kullanıcıyı tek bir tıklamayla stüdyoya davet etmenizi sağlar."}