{"scratch-messaging/send-error":"Error enviando comentario","scratch-messaging/deleting":"Borrando comentario...","scratch-messaging/delete-error":"Error borrando comentario - tal vez no tengas permiso de hacer esto.","scratch-messaging/deleted":"[borrado]","scratch-messaging/popup-title":"Scratch Addons - Mensajes","scratch-messaging/open-new-tab":"Abrir comentario en nueva pestaña","scratch-messaging/delete":"Borrar","scratch-messaging/delete-confirm":"Clickear para confirmar borrado","scratch-messaging/reply":"Responder","scratch-messaging/posting":"Enviando...","scratch-messaging/post":"Enviar","scratch-messaging/cancel":"Cancelar","scratch-messaging/chars-left":"{num, plural, one {} other {}}","scratch-messaging/follows":"Seguidores nuevos","scratch-messaging/studio-invites":"Invitaciones a estudi","scratch-messaging/forum":"Actividad en el foro","scratch-messaging/studio-activity":"Actividades en estudios","scratch-messaging/remixes":"Reinvenciones","scratch-messaging/your-profile":"Tu perfi","scratch-messaging/loading":"Cargando mensajes...","scratch-messaging/logged-out":"No se pudieron acceder a los mensajes, inicie sesión en Scratch.","scratch-messaging/settings":"configuración de Scratch Addons","scratch-messaging/loading-comments":"Cargando comentarios...","scratch-messaging/reload":"Actualizar mensajes","scratch-messaging/no-unread":"No hay mensajes sin leer","scratch-messaging/show-more":"Mostrar más mensajes","scratch-messaging/mark-as-read":"Marcar mensajes como leídos","scratch-messaging/marked-as-read":"Marcados como leídos","scratch-messaging/open-messages":"Abrir página de mensajes","scratch-messaging/@description":"Disponible al clickear el ícono de Scratch Addons. Provee fácil lectura y respuesta a tus mensajes: agrupa los mensajes por proyecto, muestra todo el contenido de los comentarios y permite responder a ellos directamente."}