{
  "name": "Change behavior of create new sprite/backdrop/costume/sound buttons",
  "description": "Changes create asset buttons to create an empty costume, upload a file, or create a random asset instead of opening the library.",
  "credits": [
    {
      "name": "GarboMuffin"
    }
  ],
  "userscripts": [
    {
      "url": "userscript.js",
      "matches": ["projects"]
    }
  ],
  "settings": [
    {
      "id": "sprite",
      "name": "Add sprite",
      "type": "select",
      "potentialValues": [
        {
          "id": "library",
          "name": "Search library"
        },
        {
          "id": "paint",
          "name": "Create empty"
        },
        {
          "id": "surprise",
          "name": "Surprise"
        },
        {
          "id": "upload",
          "name": "Upload"
        }
      ],
      "default": "paint"
    },
    {
      "id": "costume",
      "name": "Add costume",
      "type": "select",
      "potentialValues": [
        {
          "id": "library",
          "name": "Search library"
        },
        {
          "id": "paint",
          "name": "Create empty"
        },
        {
          "id": "surprise",
          "name": "Surprise"
        },
        {
          "id": "upload",
          "name": "Upload"
        }
      ],
      "default": "paint"
    },
    {
      "id": "backdrop",
      "name": "Add backdrop",
      "type": "select",
      "potentialValues": [
        {
          "id": "library",
          "name": "Search library"
        },
        {
          "id": "paint",
          "name": "Create empty"
        },
        {
          "id": "surprise",
          "name": "Surprise"
        },
        {
          "id": "upload",
          "name": "Upload"
        }
      ],
      "default": "paint"
    },
    {
      "id": "sound",
      "name": "Add sound",
      "type": "select",
      "potentialValues": [
        {
          "id": "library",
          "name": "Search library"
        },
        {
          "id": "record",
          "name": "Record"
        },
        {
          "id": "surprise",
          "name": "Surprise"
        },
        {
          "id": "upload",
          "name": "Upload"
        }
      ],
      "default": "library"
    }
  ],
  "dynamicEnable": true,
  "dynamicDisable": true,
  "versionAdded": "1.19.0",
  "tags": ["editor"],
  "enabledByDefault": false
}
