{
  "name": "Compact messages",
  "description": "Makes Scratch's messages page more compact and easier to read.",
  "credits": [
    {
      "name": "yes-i-am-lanky",
      "link": "https://scratch.mit.edu/users/yes-i-am-lanky/"
    },
    {
      "name": "DNin01",
      "link": "https://github.com/DNin01"
    }
  ],
  "settings": [
    {
      "name": "Hide message type icons",
      "id": "hide_icons",
      "type": "boolean",
      "default": false
    },
    {
      "name": "Remove borders",
      "id": "no_borders",
      "type": "boolean",
      "default": false
    },
    {
      "name": "Message padding (px)",
      "id": "message_padding",
      "type": "integer",
      "default": 5,
      "min": 0,
      "max": 16
    },
    {
      "name": "Comment box padding (px)",
      "id": "comment_padding",
      "type": "integer",
      "default": 5,
      "min": 0,
      "max": 16
    }
  ],
  "userstyles": [
    {
      "url": "styles.css",
      "matches": ["https://scratch.mit.edu/messages"]
    },
    {
      "url": "hide_icons.css",
      "matches": ["https://scratch.mit.edu/messages"],
      "if": {
        "settings": {
          "hide_icons": true
        }
      }
    },
    {
      "url": "no_border.css",
      "matches": ["https://scratch.mit.edu/messages"],
      "if": {
        "settings": {
          "no_borders": true
        }
      }
    }
  ],
  "dynamicDisable": true,
  "dynamicEnable": true,
  "updateUserstylesOnSettingsChange": true,
  "versionAdded": "1.18.0",
  "latestUpdate": {
    "version": "1.34.0",
    "newSettings": ["no_borders"]
  },
  "tags": ["community", "theme"],
  "enabledByDefault": false
}
