{
  "name": "Project notes tabs",
  "description": "Creates tabs on a project page for the \"Instructions\" section and the \"Notes and Credits\" section.",
  "credits": [
    {
      "name": "TheColaber",
      "link": "https://scratch.mit.edu/users/TheColaber"
    }
  ],
  "userscripts": [
    {
      "url": "userscript.js",
      "matches": ["projects"],
      "runAtComplete": false
    }
  ],
  "userstyles": [
    {
      "url": "style.css",
      "matches": ["projects"]
    }
  ],
  "versionAdded": "1.4.0",
  "tags": ["community", "projectPage"],
  "enabledByDefault": false
}
