{"exact-count/studio-tooltip":"Klicke, um die genaue Anzahl anzuzeigen","exact-count/@name":"Zeige die genaue Anzahl","exact-count/@description":"Zeigt genaue Zahlen auf Profilen und die genaue Projektanzahl in Studios.","exact-count/@info-studioClick":"Um die genau Anzahl von Projekten in einem Studio anzuzeigen y aktiviere unten die Einstellungen \"genaue Anzahl in Studios\" und klicke auf das Label \"100+\" auf dem Projekte-Tab des Studios.","exact-count/@settings-name-user":"Genaue Anzahlen auf Profilen","exact-count/@settings-name-studio":"Genaue Anzahlen für Studios"}