{"editor-theme3/@name":"Személyre szabható blokk színek","editor-theme3/@description":"Szerkeszd a blokkok színeit kategóriánként a szerkesztőben.","editor-theme3/@update":"A \"Sötét kommentek\" beállítás a \"Szerkesztő sötét mód és személyre szabható színek\" bővítményből ide lett áthelyezve és most már személyre szabható.","editor-theme3/@preset-name-tweaks":"3.0 Kis Igazítással","editor-theme3/@preset-description-tweaks":"Események, Vezérlés és Blokkjaim kategóriák blokkjai 2.0 inspirálta színekkel.","editor-theme3/@preset-name-original":"2.0-ás Színek","editor-theme3/@preset-description-original":"A Scratch 2.0 eredeti blokk színei","editor-theme3/@preset-name-dark":"Sötét","editor-theme3/@preset-description-dark":"Az alapvető színek sötétebb változatai","editor-theme3/@preset-name-black":"Fekete","editor-theme3/@preset-description-black":"Sötétté teszi a blokkok háttereit","editor-theme3/@settings-name-motion-color":"Mozgás","editor-theme3/@settings-name-looks-color":"Kinézet","editor-theme3/@settings-name-sounds-color":"Hangok","editor-theme3/@settings-name-events-color":"Események","editor-theme3/@settings-name-control-color":"Vezérlés","editor-theme3/@settings-name-sensing-color":"Érzékelés","editor-theme3/@settings-name-operators-color":"Műveletek","editor-theme3/@settings-name-data-color":"Változók","editor-theme3/@settings-name-data-lists-color":"Listák","editor-theme3/@settings-name-custom-color":"Blokkjaim","editor-theme3/@settings-name-Pen-color":"Bővítmények","editor-theme3/@settings-name-sa-color":"Scratch Addons blokkjai","editor-theme3/@settings-name-input-color":"Blokk bemenetek","editor-theme3/@settings-name-comment-color":"Kommentek","editor-theme3/@settings-name-text":"Szöveg színe","editor-theme3/@settings-select-text-white":"Fehér","editor-theme3/@settings-select-text-black":"Fekete","editor-theme3/@settings-select-text-colorOnWhite":"Színes fehér háttéren","editor-theme3/@settings-select-text-colorOnBlack":"Színes fekete háttéren","editor-theme3/@settings-name-forums":"Változtasd meg a blokkok színeit a fórumokon"}