{"forum-search/loading":"Laden...","forum-search/error":"Fout met laden van ScratchDB!","forum-search/none":"Je zoekopdracht gaf geen resultaat","forum-search/username":"Gebruikersnaam:","forum-search/posts-here":"Gebruikersposts Hier","forum-search/posts-sitewide":"Gebruikersposts Over Hele Site","forum-search/first-checked":"Voor het eerst gecheckt:","forum-search/last-checked":"Voor het laatst gecheckt:","forum-search/last-edited-by":"Laatst bewerkt door {username} ({datetime})","forum-search/placeholder":"Zoek naar posts over de hele Scratch Forums","forum-search/search-topic":"Zoek naar posts in \"{topic}\"","forum-search/search-cat":"Zoek naar posts in \"{cat}\"","forum-search/relevance":"relevantie","forum-search/newest":"nieuwste","forum-search/oldest":"oudste","forum-search/@name":"Forums Doorzoeken","forum-search/@description":"Voegt een zoekbalk toe aan de forums. Gebruikt ScratchDB voor informatie."}